django_http2/__init__.py
django_http2/middleware.py
django_http2/templatetags/http2.py
django_http2-0.0.1.dist-info/LICENSE
django_http2-0.0.1.dist-info/WHEEL
django_http2-0.0.1.dist-info/METADATA
django_http2-0.0.1.dist-info/RECORD
